allow_cidr/__init__.py
allow_cidr/apps.py
allow_cidr/middleware.py
django_allow_cidr-0.8.0.dist-info/licenses/LICENSE
django_allow_cidr-0.8.0.dist-info/METADATA
django_allow_cidr-0.8.0.dist-info/WHEEL
django_allow_cidr-0.8.0.dist-info/top_level.txt
django_allow_cidr-0.8.0.dist-info/RECORD
